{
  "uid": {
    "__TYPE__": "UIDContent",
    "value": "getting"
  },
  "status": {
    "__TYPE__": "FieldContent",
    "value": "ORDER",
    "type": "Select"
  },
  "number": {
    "__TYPE__": "FieldContent",
    "value": "68",
    "type": "Number"
  },
  "title": {
    "__TYPE__": "StructuredTextContent",
    "value": [
      {
        "type": "paragraph",
        "content": {
          "text": "Nisi dolore ea velit nisi nostrud commodo tempor voluptate. Ipsum adipisicing aliqua aliquip proident pariatur reprehenderit aliqua nulla magna sint ad non."
        }
      }
    ]
  },
  "description": {
    "__TYPE__": "StructuredTextContent",
    "value": [
      {
        "type": "paragraph",
        "content": {
          "text": "Irure culpa et excepteur consectetur anim officia velit enim Lorem fugiat tempor sunt."
        }
      }
    ]
  },
  "image": {
    "__TYPE__": "ImageContent",
    "origin": {
      "id": "main",
      "url": "https://images.unsplash.com/photo-1491975474562-1f4e30bc9468",
      "width": 4000,
      "height": 6000
    },
    "url": "https://images.unsplash.com/photo-1491975474562-1f4e30bc9468",
    "width": 4000,
    "height": 6000,
    "edit": {
      "zoom": 1,
      "crop": {
        "x": 0,
        "y": 0
      },
      "background": "transparent"
    },
    "thumbnails": {}
  },
  "extra_line": {
    "__TYPE__": "StructuredTextContent",
    "value": [
      {
        "type": "paragraph",
        "content": {
          "text": "Amet officia consectetur ex et nisi sit excepteur anim aute. Est ut anim ut et cupidatat sint commodo est amet. Pariatur qui duis id eu duis Lorem laboris adipisicing consequat nisi anim labore labore."
        }
      }
    ]
  },
  "price": {
    "__TYPE__": "FieldContent",
    "value": "15",
    "type": "Number"
  },
  "color": {
    "__TYPE__": "FieldContent",
    "value": "#1fbaaa",
    "type": "Color"
  },
  "slices": {
    "__TYPE__": "SliceContentType",
    "value": [
      {
        "key": "slider$29bfa390-a9e5-41a2-b950-c2fd903ebf6a",
        "name": "slider",
        "widget": {
          "__TYPE__": "SharedSliceContent",
          "variation": "default",
          "primary": {
            "video": {
              "__TYPE__": "LinkContent",
              "value": {
                "id": "mock_Media_link",
                "kind": "image/jpeg",
                "name": "mock_name",
                "url": "https://source.unsplash.com/daily",
                "size": "0",
                "__TYPE__": "FileLink"
              }
            }
          },
          "items": [
            {
              "__TYPE__": "GroupItemContent",
              "value": [
                [
                  "image",
                  {
                    "__TYPE__": "ImageContent",
                    "origin": {
                      "id": "main",
                      "url": "https://images.unsplash.com/photo-1601933973783-43cf8a7d4c5f",
                      "width": 6597,
                      "height": 4398
                    },
                    "url": "https://images.unsplash.com/photo-1601933973783-43cf8a7d4c5f",
                    "width": 6597,
                    "height": 4398,
                    "edit": {
                      "zoom": 1,
                      "crop": {
                        "x": 0,
                        "y": 0
                      },
                      "background": "transparent"
                    },
                    "thumbnails": {}
                  }
                ]
              ]
            }
          ]
        }
      },
      {
        "key": "book_info$a0bc25ce-0a26-428e-91be-b7d1f9b4beda",
        "name": "book_info",
        "widget": {
          "__TYPE__": "SharedSliceContent",
          "variation": "default",
          "primary": {
            "year": {
              "__TYPE__": "StructuredTextContent",
              "value": [
                {
                  "type": "paragraph",
                  "content": {
                    "text": "Mollit commodo occaecat irure mollit duis reprehenderit dolor culpa et sint laboris reprehenderit ut excepteur aliquip."
                  }
                }
              ]
            },
            "edition": {
              "__TYPE__": "StructuredTextContent",
              "value": [
                {
                  "type": "paragraph",
                  "content": {
                    "text": "Ut id dolor sit ex aliqua enim qui laborum voluptate esse."
                  }
                }
              ]
            },
            "pages": {
              "__TYPE__": "StructuredTextContent",
              "value": [
                {
                  "type": "paragraph",
                  "content": {
                    "text": "Nostrud mollit veniam tempor duis ex pariatur aliqua ad enim anim eiusmod elit Lorem ad. Consequat dolore excepteur aute. Elit anim anim exercitation excepteur mollit velit cupidatat."
                  }
                }
              ]
            },
            "dimensions": {
              "__TYPE__": "StructuredTextContent",
              "value": [
                {
                  "type": "paragraph",
                  "content": {
                    "text": "Labore cupidatat pariatur sunt nisi eu adipisicing magna in laborum voluptate ut. Minim ex nisi consequat tempor incididunt velit duis sit excepteur nisi laboris."
                  }
                }
              ]
            },
            "paper": {
              "__TYPE__": "StructuredTextContent",
              "value": [
                {
                  "type": "paragraph",
                  "content": {
                    "text": "Nulla aliqua minim nostrud ipsum id Lorem officia."
                  }
                }
              ]
            },
            "copyright": {
              "__TYPE__": "StructuredTextContent",
              "value": [
                {
                  "type": "paragraph",
                  "content": {
                    "text": "Culpa proident dolore minim nostrud deserunt labore voluptate aliquip duis consectetur aliqua pariatur esse."
                  }
                }
              ]
            },
            "isbn": {
              "__TYPE__": "StructuredTextContent",
              "value": [
                {
                  "type": "paragraph",
                  "content": {
                    "text": "Nostrud occaecat officia pariatur aliquip officia. Cupidatat reprehenderit commodo reprehenderit cillum nulla nisi est."
                  }
                }
              ]
            }
          },
          "items": [
            {
              "__TYPE__": "GroupItemContent",
              "value": []
            }
          ]
        }
      }
    ]
  }
}